ocralign/__init__.py
ocralign/ocr.py
ocralign/tess_align.py
ocralign-0.1.0.dist-info/licenses/LICENSE
ocralign-0.1.0.dist-info/METADATA
ocralign-0.1.0.dist-info/WHEEL
ocralign-0.1.0.dist-info/top_level.txt
ocralign-0.1.0.dist-info/RECORD
