Metadata-Version: 2.4
Name: ocralign
Version: 0.1.0
Summary: OCR while preserving document formatting and layout
Author-email: Hasham Ul Haq <haashaamulhaq@gmail.com>
License:                                  Apache License
Requires-Python: >=3.7
License-File: LICENSE
Requires-Dist: pdf2image
Requires-Dist: pytesseract
Requires-Dist: numpy
Requires-Dist: beautifulsoup4
Requires-Dist: tqdm
Dynamic: license-file
